pyialarm/__init__.py
pyialarm/pyialarm.py
pyialarm-2.2.0.dist-info/LICENSE
pyialarm-2.2.0.dist-info/METADATA
pyialarm-2.2.0.dist-info/WHEEL
pyialarm-2.2.0.dist-info/top_level.txt
pyialarm-2.2.0.dist-info/RECORD
